astrbot_mcp/__init__.py
astrbot_mcp/astrbot_client.py
astrbot_mcp/config.py
astrbot_mcp/server.py
astrbot_mcp/tools.py
astrbot_mcp/tools/__init__.py
astrbot_mcp/tools/config_search_tool.py
astrbot_mcp/tools/config_tools.py
astrbot_mcp/tools/control_tools.py
astrbot_mcp/tools/helpers.py
astrbot_mcp/tools/log_tools.py
astrbot_mcp/tools/platform_tools.py
astrbot_mcp/tools/plugin_market_tools.py
astrbot_mcp/tools/session_tools.py
astrbot_mcp/tools/types.py
astrbot_mcp/tools/message/__init__.py
astrbot_mcp/tools/message/cache.py
astrbot_mcp/tools/message/direct.py
astrbot_mcp/tools/message/quote.py
astrbot_mcp/tools/message/utils.py
astrbot_mcp/tools/message/webchat.py
astrbotmcp-0.3.1.dist-info/licenses/LICENSE.txt
astrbotmcp-0.3.1.dist-info/METADATA
astrbotmcp-0.3.1.dist-info/WHEEL
astrbotmcp-0.3.1.dist-info/entry_points.txt
astrbotmcp-0.3.1.dist-info/top_level.txt
astrbotmcp-0.3.1.dist-info/RECORD
