Metadata-Version: 2.4
Name: astrbotmcp
Version: 0.3.1
Summary: Add your description here
Requires-Python: >=3.10
License-File: LICENSE.txt
Requires-Dist: fastmcp>=2.13.3
Requires-Dist: httpx>=0.28.1
Provides-Extra: test
Requires-Dist: build>=1.2.2; extra == "test"
Requires-Dist: pytest>=7.4; extra == "test"
Dynamic: license-file
